.flake8
ChangeLog
LICENSE
MANIFEST.in
Makefile
README.markdown
pyproject.toml
doc/Makefile
doc/conf.py
doc/index.rst
l10n/ca.po
l10n/de.po
l10n/es.po
l10n/fr.po
l10n/messages.pot
l10n/oc.po
l10n/sv.po
l10n/uk.po
l10n/zh_Hans.po
src/paperwork_backend/__init__.py
src/paperwork_backend/_version.py
src/paperwork_backend/app.py
src/paperwork_backend/datadirhandler.py
src/paperwork_backend/deps.py
src/paperwork_backend/doctracker.py
src/paperwork_backend/pagetracker.py
src/paperwork_backend/pyocr.py
src/paperwork_backend/sync.py
src/paperwork_backend/util.py
src/paperwork_backend.egg-info/PKG-INFO
src/paperwork_backend.egg-info/SOURCES.txt
src/paperwork_backend.egg-info/dependency_links.txt
src/paperwork_backend.egg-info/requires.txt
src/paperwork_backend.egg-info/top_level.txt
src/paperwork_backend/authors/AUTHORS.git.json
src/paperwork_backend/authors/AUTHORS.json
src/paperwork_backend/authors/Makefile
src/paperwork_backend/authors/__init__.py
src/paperwork_backend/authors/translators.py
src/paperwork_backend/beacon/__init__.py
src/paperwork_backend/beacon/update.py
src/paperwork_backend/cairo/__init__.py
src/paperwork_backend/cairo/blur.py
src/paperwork_backend/cairo/cache.py
src/paperwork_backend/cairo/pillow.py
src/paperwork_backend/cairo/poppler.py
src/paperwork_backend/chkworkdir/__init__.py
src/paperwork_backend/chkworkdir/corrupted_page_map.py
src/paperwork_backend/chkworkdir/empty_doc.py
src/paperwork_backend/chkworkdir/file_at_workdir_root.py
src/paperwork_backend/chkworkdir/label_color.py
src/paperwork_backend/converter/__init__.py
src/paperwork_backend/converter/libreoffice.py
src/paperwork_backend/docexport/__init__.py
src/paperwork_backend/docexport/automatic.py
src/paperwork_backend/docexport/generic.py
src/paperwork_backend/docexport/img.py
src/paperwork_backend/docexport/pdf.py
src/paperwork_backend/docexport/pillowfight.py
src/paperwork_backend/docimport/__init__.py
src/paperwork_backend/docimport/converted.py
src/paperwork_backend/docimport/img.py
src/paperwork_backend/docimport/pdf.py
src/paperwork_backend/docscan/__init__.py
src/paperwork_backend/docscan/autoselect_scanner.py
src/paperwork_backend/docscan/fake.py
src/paperwork_backend/docscan/libinsane.py
