Metadata-Version: 2.1
Name: paperwork-backend
Version: 2.2.4
Summary: Paperwork's backend
Author-email: Jerome Flesch <jflesch@openpaper.work>
License: GPL-3.0-or-later
License-File: LICENSE
Requires-Dist: openpaperwork-core
Requires-Dist: Pillow
Requires-Dist: psutil
Requires-Dist: pycountry
Requires-Dist: pyocr
Requires-Dist: pypillowfight>=0.3.0
Requires-Dist: scikit-learn
Requires-Dist: Whoosh
Provides-Extra: dev
Requires-Dist: pytest; extra == "dev"
Provides-Extra: lint
Requires-Dist: flake8; extra == "lint"
